golem/__init__.py
golem/version.py
golem/api/__init__.py
golem/api/main.py
golem/api/api_utils/__init__.py
golem/api/api_utils/api_params.py
golem/core/__init__.py
golem/core/constants.py
golem/core/log.py
golem/core/paths.py
golem/core/adapter/__init__.py
golem/core/adapter/adapt_registry.py
golem/core/adapter/adapter.py
golem/core/adapter/nx_adapter.py
golem/core/dag/__init__.py
golem/core/dag/convert.py
golem/core/dag/graph.py
golem/core/dag/graph_delegate.py
golem/core/dag/graph_node.py
golem/core/dag/graph_utils.py
golem/core/dag/graph_verifier.py
golem/core/dag/linked_graph.py
golem/core/dag/linked_graph_node.py
golem/core/dag/verification_rules.py
golem/core/optimisers/__init__.py
golem/core/optimisers/advisor.py
golem/core/optimisers/dynamic_graph_requirements.py
golem/core/optimisers/graph.py
golem/core/optimisers/graph_builder.py
golem/core/optimisers/initial_graphs_generator.py
golem/core/optimisers/opt_graph_builder.py
golem/core/optimisers/opt_node_factory.py
golem/core/optimisers/optimization_parameters.py
golem/core/optimisers/optimizer.py
golem/core/optimisers/populational_optimizer.py
golem/core/optimisers/random_graph_factory.py
golem/core/optimisers/timer.py
golem/core/optimisers/adaptive/__init__.py
golem/core/optimisers/adaptive/agent_trainer.py
golem/core/optimisers/adaptive/common_types.py
golem/core/optimisers/adaptive/context_agents.py
golem/core/optimisers/adaptive/experience_buffer.py
golem/core/optimisers/adaptive/history_collector.py
golem/core/optimisers/adaptive/neural_mab.py
golem/core/optimisers/adaptive/operator_agent.py
golem/core/optimisers/adaptive/reward_agent.py
golem/core/optimisers/adaptive/utils.py
golem/core/optimisers/adaptive/mab_agents/__init__.py
golem/core/optimisers/adaptive/mab_agents/contextual_mab_agent.py
golem/core/optimisers/adaptive/mab_agents/mab_agent.py
golem/core/optimisers/adaptive/mab_agents/neural_contextual_mab_agent.py
golem/core/optimisers/archive/__init__.py
thegolem-0.4.2.dist-info/LICENSE
thegolem-0.4.2.dist-info/METADATA
thegolem-0.4.2.dist-info/WHEEL
thegolem-0.4.2.dist-info/top_level.txt
thegolem-0.4.2.dist-info/RECORD
