Metadata-Version: 2.1
Name: thegolem
Version: 0.4.2
Summary: Framework for Graph Optimization and Learning by Evolutionary Methods
Home-page: https://github.com/aimclub/GOLEM
Author: NSS Lab
Author-email: itmo.nss.team@gmail.com
License: BSD 3-Clause
Classifier: License :: OSI Approved :: BSD License
Classifier: Programming Language :: Python :: 3.8
Classifier: Programming Language :: Python :: 3.9
Classifier: Programming Language :: Python :: 3.10
Requires-Python: >=3.8
License-File: LICENSE
Requires-Dist: numpy!=1.24.0,<2.0.0,>=1.16.0
Requires-Dist: networkx!=2.7.*,!=2.8.1,!=2.8.2,!=2.8.3,<3.3,>=2.4
Requires-Dist: scipy<1.13.0
Requires-Dist: zss>=1.2.0
Requires-Dist: pyvis==0.2.1
Requires-Dist: MarkupSafe==2.1.1
Requires-Dist: seaborn>=0.9.0
Requires-Dist: imageio>=2.28.1
Requires-Dist: Pillow>=9.5.0
Requires-Dist: func-timeout==4.3.5
Requires-Dist: joblib>=0.17.0
Requires-Dist: requests>=2.0
Requires-Dist: tqdm~=4.66.3
Requires-Dist: typing>=3.7.0
Requires-Dist: psutil>=5.9.2
Requires-Dist: hyperopt>=0.2.7
Requires-Dist: iOpt==0.2.22
Requires-Dist: optuna>=3.2.0
Requires-Dist: pytest>=6.2.0
Requires-Dist: testfixtures>=6.18.0
Requires-Dist: mabwiser>=2.7.0
Requires-Dist: pandas>=1.3.0; python_version >= "3.8"
Requires-Dist: matplotlib>=3.3.1; python_version >= "3.8"
Provides-Extra: adaptive
Requires-Dist: torch; extra == "adaptive"
Requires-Dist: karateclub>=1.3.3; extra == "adaptive"
Provides-Extra: docs
Requires-Dist: sphinx==4.2.0; extra == "docs"
Requires-Dist: sphinx-rtd-theme==1.0.0; extra == "docs"
Requires-Dist: readthedocs-sphinx-search==0.1.1; extra == "docs"
Requires-Dist: sphinxcontrib-details-directive; extra == "docs"
Requires-Dist: autodocsumm; extra == "docs"
Provides-Extra: molecules
Requires-Dist: rdkit>=2018.09.1.0; extra == "molecules"
Requires-Dist: guacamol>=0.5.4; extra == "molecules"
Requires-Dist: joblib>=0.12.5; extra == "molecules"
Requires-Dist: requests>=2.30.0; extra == "molecules"
Requires-Dist: mol2vec==0.2.2; extra == "molecules"
Requires-Dist: gensim<=4.3.2; extra == "molecules"
Requires-Dist: torch>=2.0.1; extra == "molecules"
Provides-Extra: profilers
Requires-Dist: snakeviz==2.1.0; extra == "profilers"
Requires-Dist: gprof2dot==2021.2.21; extra == "profilers"
Requires-Dist: objgraph==3.5.0; extra == "profilers"
Requires-Dist: memory-profiler==0.58.0; extra == "profilers"
